CHANGES.txt
LICENSE.txt
MANIFEST.in
README.md
setup.py
bin/dl-skel.py
bin/.ropeproject/config.py
bin/.ropeproject/globalnames
bin/.ropeproject/history
bin/.ropeproject/objectdb
dl_skel.egg-info/PKG-INFO
dl_skel.egg-info/SOURCES.txt
dl_skel.egg-info/dependency_links.txt
dl_skel.egg-info/requires.txt
dl_skel.egg-info/top_level.txt
dlskel/__init__.py
dlskel/conf.py
dlskel/helpers.py
dlskel/skel.py
docs/dlskel.png
docs/index.rst