Metadata-Version: 1.0
Name: dl-skel
Version: 0.1.2
Summary: DoubleLeft skeleton generator
Home-page: http://doubleleft.github.com/dl-skel
Author: vitorfaleiros
Author-email: barrabin.fc@gmail.com
License: UNKNOWN
Platform: UNKNOWN
Classifier: Development Status :: 3 - Alpha
Classifier: License :: OSI Approved :: GNU General Public License v3 (GPLv3)
Classifier: Programming Language :: Python
